{
  "projects": [
    {
      "id": "1",
      "title": "Тестовый проект №1"
    },
    {
      "id": "2",
      "title": "Тестовый проект №2"
    },
    {
      "id": "3",
      "title": "Тестовый проект №3"
    }
  ],
  "tasks": [
    {
      "id": "1",
      "projectId": "1",
      "type": "Разработка ПО",
      "title": "Название задачи №1",
      "description": "Описание задачи по разработке ПО. Тут много текста. Максимум 250 букв например. Описание задачи по разработке ПО. Тут много текста. Максимум 250 букв например. Описание задачи по разработке ПО. Тут много текста. Максимум 250 букв например.",
      "status": "completed"
    },
    {
      "id": "2",
      "projectId": "1",
      "type": "Веб-разработка",
      "title": "Название задачи №2",
      "description": "Описание задачи по веб-разработке. Тут много текста. Максимум 250 букв например. Описание задачи по веб-разработке. Тут много текста. Максимум 250 букв например. Описание задачи по веб-разработке. Тут много текста. Максимум 250 букв например.",
      "status": "to_do"
    },
    {
      "id": "3",
      "projectId": "1",
      "type": "Анализ данных",
      "title": "Название задачи №3",
      "description": "Описание задачи по анализу данных. Тут много текста. Максимум 250 букв например. Описание задачи по анализу данных. Тут много текста. Максимум 250 букв например. Описание задачи по анализу данных. Тут много текста. Максимум 250 букв например.",
      "status": "in_progress"
    },
    {
      "id": "4",
      "projectId": "2",
      "type": "Веб-разработка",
      "title": "Название задачи №4",
      "description": "Описание задачи по веб-разработке. Тут много текста. Максимум 250 букв например. Описание задачи по веб-разработке. Тут много текста. Максимум 250 букв например. Описание задачи по веб-разработке. Тут много текста. Максимум 250 букв например.",
      "status": "in_progress"
    },
    {
      "id": "5",
      "projectId": "3",
      "type": "Разработка ПО",
      "title": "Название задачи №5",
      "description": "Описание задачи по разработке ПО. Тут много текста. Максимум 250 букв например. Описание задачи по разработке ПО. Тут много текста. Максимум 250 букв например. Описание задачи по разработке ПО. Тут много текста. Максимум 250 букв например.",
      "status": "to_do"
    },
    {
      "id": "6",
      "projectId": "3",
      "type": "Веб-разработка",
      "title": "Название задачи №6",
      "description": "Описание задачи по веб-разработке. Тут много текста. Максимум 250 букв например. Описание задачи по веб-разработке. Тут много текста. Максимум 250 букв например. Описание задачи по веб-разработке. Тут много текста. Максимум 250 букв например.",
      "status": "completed"
    },
    {
      "id": "7",
      "projectId": "3",
      "type": "Анализ данных",
      "title": "Название задачи №7",
      "description": "Описание задачи по анализу данных. Тут много текста. Максимум 250 букв например. Описание задачи по анализу данных. Тут много текста. Максимум 250 букв например. Описание задачи по анализу данных. Тут много текста. Максимум 250 букв например.",
      "status": "completed"
    }
  ],
  "users": [
    {
      "id": "1",
      "name": "Пользователь №1",
      "added_at": "23:45"
    },
    {
      "id": "2",
      "name": "Пользователь №2",
      "added_at": "23:45"
    },
    {
      "id": "3",
      "name": "Пользователь №3",
      "added_at": "23:45"
    }
  ]
}